anydex/__init__.py
anydex/__init__.pyc
anydex/config.py
anydex/config.pyc
anydex/core/__init__.py
anydex/core/__init__.pyc
anydex/core/assetamount.py
anydex/core/assetamount.pyc
anydex/core/assetpair.py
anydex/core/assetpair.pyc
anydex/core/block.py
anydex/core/block.pyc
anydex/core/bloomfilter.py
anydex/core/bloomfilter.pyc
anydex/core/clearing_policy.py
anydex/core/clearing_policy.pyc
anydex/core/community.py
anydex/core/community.pyc
anydex/core/conversion.pyc
anydex/core/database.py
anydex/core/database.pyc
anydex/core/match_queue.py
anydex/core/match_queue.pyc
anydex/core/matching_engine.py
anydex/core/matching_engine.pyc
anydex/core/message.py
anydex/core/message.pyc
anydex/core/message_repository.pyc
anydex/core/order.py
anydex/core/order.pyc
anydex/core/order_manager.py
anydex/core/order_manager.pyc
anydex/core/order_repository.py
anydex/core/order_repository.pyc
anydex/core/orderbook.py
anydex/core/orderbook.pyc
anydex/core/payload.py
anydex/core/payload.pyc
anydex/core/payment.py
anydex/core/payment.pyc
anydex/core/payment_id.py
anydex/core/payment_id.pyc
anydex/core/price.py
anydex/core/price.pyc
anydex/core/pricelevel.py
anydex/core/pricelevel.pyc
anydex/core/pricelevel_list.py
anydex/core/pricelevel_list.pyc
anydex/core/quantity.pyc
anydex/core/settings.py
anydex/core/settings.pyc
anydex/core/side.py
anydex/core/side.pyc
anydex/core/socket_address.pyc
anydex/core/tick.py
anydex/core/tick.pyc
anydex/core/tickentry.py
anydex/core/tickentry.pyc
anydex/core/timeout.py
anydex/core/timeout.pyc
anydex/core/timestamp.py
anydex/core/timestamp.pyc
anydex/core/trade.py
anydex/core/trade.pyc
anydex/core/tradingengine.pyc
anydex/core/transaction.py
anydex/core/transaction.pyc
anydex/core/transaction_manager.py
anydex/core/transaction_manager.pyc
anydex/core/transaction_repository.py
anydex/core/transaction_repository.pyc
anydex/core/trustchain_mem_db.pyc
anydex/core/wallet_address.py
anydex/core/wallet_address.pyc
anydex/restapi/__init__.py
anydex-0.1.0.dist-info/LICENSE
anydex-0.1.0.dist-info/METADATA
anydex-0.1.0.dist-info/WHEEL
anydex-0.1.0.dist-info/top_level.txt
anydex-0.1.0.dist-info/RECORD
