Metadata-Version: 2.1
Name: anydex
Version: 0.1.0
Summary: The Universal Decentralized Exchange
Home-page: https://github.com/Tribler/anydex-core
Author: Tribler
License: UNKNOWN
Platform: UNKNOWN
Classifier: Development Status :: 5 - Production/Stable
Classifier: Framework :: Twisted
Classifier: Intended Audience :: Developers
Classifier: License :: OSI Approved :: GNU Lesser General Public License v3 (LGPLv3)
Classifier: Natural Language :: English
Classifier: Operating System :: OS Independent
Classifier: Programming Language :: Python :: 2.7
Classifier: Programming Language :: Python :: 3.5
Classifier: Programming Language :: Python :: 3.6
Classifier: Programming Language :: Python :: 3.7
Classifier: Topic :: Scientific/Engineering
Classifier: Topic :: Software Development :: Libraries :: Python Modules
Classifier: Topic :: System :: Distributed Computing
Requires-Dist: autobahn
Requires-Dist: bitcoinlib (==0.4.5)
Requires-Dist: cryptography
Requires-Dist: libnacl
Requires-Dist: netifaces
Requires-Dist: Twisted
Requires-Dist: pyOpenSSL
Requires-Dist: six
